Metadata-Version: 2.1
Name: so-lazy
Version: 0.0.2
Summary: Lazy loading Python package
Home-page: https://github.com/troywilson/so-lazy
Author: Troy Wilson
License: Apache License 2.0
Download-URL: https://pypi.org/project/so-lazy/
Platform: UNKNOWN
Classifier: Development Status :: 4 - Beta
Classifier: Intended Audience :: Developers
Classifier: License :: OSI Approved :: Apache Software License
Classifier: Operating System :: OS Independent
Classifier: Programming Language :: Python :: 3.5
Classifier: Programming Language :: Python :: 3.6
Classifier: Programming Language :: Python :: 3.7
Classifier: Programming Language :: Python :: 3.8
Classifier: Topic :: Software Development :: Libraries :: Python Modules
Requires-Python: >=3.5
